<?xml version="1.0" encoding="UTF-8"?>
<item>
	<title>Celcius🥤</title>
	<content>### When you’re stressed or have a hard time getting out of bed, Celcius coffee is there for you, ready when you are.

The all-natural coffee grounds are blended with a secret blend of essential oils and aromas that can be enjoyed anytime of day, by itself or as desired.

Best of all, we guarantee that it's caffeine free!
(Because is a digital product)</content>
	<excerpt>Really Instant Coffee</excerpt>
	<description>With Celcius you can satisfy your need for Digital Coffee in the Morning, at Night, or at any time of the day, a great way to start or continue your proactivity.</description>
	<media>
		<url type="png">media/5daad8ca/celcius.png</url>
		<url type="png">media/f42304d3/celcius.png</url>
	</media>
	<info>
		<slug>celcius-instant</slug>
		<date>20/10/2022</date>
		<url>https://phixel.net/en/portfolio/celcius-really-instant-coffee/</url>
		<category>Portfolio Item</category>
		<url>portfolio-item</url>
		<emojis>🆒☕🥤</emojis>
		<hashtags>
			<hashtag>phixel</hashtag>
			<hashtag>celcius</hashtag>
			<hashtag>instacoffee</hashtag>
			<hashtag>celsius</hashtag>
			<hashtag>coffeelover</hashtag>
			<hashtag>cafe</hashtag>
		</hashtags>
		<tags>
			<tag>Celcius</tag>
			<tag>Instant</tag>
			<tag>Coffee</tag>
			<tag>Digital</tag>
			<tag>Proactivity</tag>
			<tag>Stress</tag>
			<tag>Caffeine-Free</tag>
			<tag>All-Natural</tag>
			<tag>Aromas</tag>
		</tags>
	</info>
</item>
