{
    "title": "UX Design (user experience) \ud83c\udfa8",
    "content": "## We want to make your life easier, and we believe that good design is the key to success.\n\nWith our help, you\u2019ll be able to communicate your ideas to the world more effectively and achieve your goals with ease.\n\nPhixel focuses on creating user experiences that are engaging, intuitive, and effective.\n\nWe understand that great design is about more than just making things look good; it\u2019s about making sure that users have a positive and productive experience with your product or service.\n\nWith over 10 years of experience in the industry, we know how to create designs that not only look great but also meet the needs of your users.",
    "excerpt": "We create user experiences.",
    "description": "We design digital products with simplicity and clarity in mind.",
    "media": [
        "https:\/\/phixel.net\/wp-content\/uploads\/Services-UX-Design.jpg"
    ],
    "info": {
        "slug": "service-ux-design",
        "date": "04\/12\/2022",
        "url": "https:\/\/phixel.net\/en\/service\/ux-design\/",
        "category": "Service",
        "category_url": "service",
        "emojis": "\ud83c\udfa8\ud83d\udef8\ud83d\udcfc\ud83d\udcfa\ud83d\udcf9\ud83d\udc4d\ud83d\udd17\ud83d\udcdd\ud83c\udfe0\u270d\ufe0f\ud83d\udc68\u200d\ud83d\udcbb\u2699\ufe0f\ud83d\udd2e\ud83c\udfac\u200d\ud83d\udcbb\ud83d\udc51\ud83d\uddc3\ufe0f\ud83d\udd79\ufe0f\ud83d\udc7e\ud83c\udfae\ud83d\udcf2\ud83e\ude90\ud83c\udf1f\ud83d\udc7d\ud83d\ude80\ud83c\udf0c",
        "hashtags": {
            "1": "withlove",
            "3": "webdesigners",
            "4": "webdesignstudio",
            "5": "studio",
            "6": "design",
            "7": "designer",
            "8": "welcome",
            "9": "webdevelopers",
            "10": "videoeditors",
            "12": "clients",
            "13": "ui",
            "14": "ux",
            "15": "gui",
            "16": "motiongraphics",
            "17": "animation",
            "18": "illustration",
            "19": "3d",
            "21": "foryou",
            "22": "creativestudio"
        },
        "tags": [
            "\u00a0"
        ]
    }
}